{
  "id": "129c8304-b369-4996-b298-818a135e40b6",
  "prevId": "00000000-0000-0000-0000-000000000000",
  "version": "7",
  "dialect": "postgresql",
  "tables": {
    "public.tasks": {
      "name": "tasks",
      "schema": "",
      "columns": {
        "id": {
          "name": "id",
          "type": "uuid",
          "primaryKey": true,
          "notNull": true,
          "default": "gen_random_uuid()"
        },
        "title": {
          "name": "title",
          "type": "varchar(255)",
          "primaryKey": false,
          "notNull": true
        },
        "description": {
          "name": "description",
          "type": "text",
          "primaryKey": false,
          "notNull": false
        },
        "priority": {
          "name": "priority",
          "type": "priority",
          "typeSchema": "public",
          "primaryKey": false,
          "notNull": true
        },
        "status": {
          "name": "status",
          "type": "status",
          "typeSchema": "public",
          "primaryKey": false,
          "notNull": true
        },
        "created_at": {
          "name": "created_at",
          "type": "timestamp with time zone",
          "primaryKey": false,
          "notNull": false,
          "default": "now()"
        },
        "due_date": {
          "name": "due_date",
          "type": "timestamp with time zone",
          "primaryKey": false,
          "notNull": false
        },
        "assigned_to": {
          "name": "assigned_to",
          "type": "varchar(255)",
          "primaryKey": false,
          "notNull": false
        },
        "tags": {
          "name": "tags",
          "type": "jsonb",
          "primaryKey": false,
          "notNull": false
        },
        "estimated_hours": {
          "name": "estimated_hours",
          "type": "numeric(5, 2)",
          "primaryKey": false,
          "notNull": false
        }
      },
      "indexes": {},
      "foreignKeys": {},
      "compositePrimaryKeys": {},
      "uniqueConstraints": {},
      "policies": {},
      "checkConstraints": {},
      "isRLSEnabled": false
    }
  },
  "enums": {
    "public.priority": {
      "name": "priority",
      "schema": "public",
      "values": [
        "LOW",
        "MEDIUM",
        "HIGH"
      ]
    },
    "public.status": {
      "name": "status",
      "schema": "public",
      "values": [
        "TODO",
        "IN_PROGRESS",
        "DONE"
      ]
    }
  },
  "schemas": {},
  "sequences": {},
  "roles": {},
  "policies": {},
  "views": {},
  "_meta": {
    "columns": {},
    "schemas": {},
    "tables": {}
  }
}